Metadata-Version: 2.1
Name: tfIdfInheritVectorizer
Version: 0.1
Author: Berke Dilekoglu
License: MIT
Keywords: machine-learning tf-idf
License-File: LICENSE.txt
